setup.py
opening_hours/OpeningHours.py
opening_hours/__init__.py
opening_hours.egg-info/PKG-INFO
opening_hours.egg-info/SOURCES.txt
opening_hours.egg-info/dependency_links.txt
opening_hours.egg-info/requires.txt
opening_hours.egg-info/top_level.txt