Metadata-Version: 1.0
Name: opening-hours
Version: 0.1.0
Summary: Python wrapper embedding the C_OpeningHours writing on my own, implementation of the opening hours standard as described here: https://wiki.openstreetmap.org/wiki/Key:opening_hours
Home-page: https://github.com/anthill/Python_OpeningHours
Author: Luka Boulagnon (Asphahyre) during internship at WeAreAnts.fr
Author-email: asphahyre@geluti.org
License: MIT
Keywords: OSM,OpenStreetMap,opening_hours
Platform: UNKNOWN
